{
  "main": {
    "id": "afb6bb504e3a100f",
    "type": "split",
    "children": [
      {
        "id": "57e135ed4169d40e",
        "type": "tabs",
        "children": [
          {
            "id": "4f8f443e8b801402",
            "type": "leaf",
            "state": {
              "type": "markdown",
              "state": {
                "file": "_posts/2023-10-23-传输层3.4.md",
                "mode": "source",
                "source": true
              }
            }
          }
        ]
      },
      {
        "id": "c81a6f6f951b4a59",
        "type": "tabs",
        "children": [
          {
            "id": "0c19781e807f0270",
            "type": "leaf",
            "state": {
              "type": "markdown",
              "state": {
                "file": "_posts/2023-10-23-传输层3.3.md",
                "mode": "preview",
                "source": false
              }
            }
          },
          {
            "id": "9e727a1188f2c470",
            "type": "leaf",
            "state": {
              "type": "markdown",
              "state": {
                "file": "_posts/2023-10-23-传输层3.4.md",
                "mode": "source",
                "source": false
              }
            }
          }
        ],
        "currentTab": 1
      }
    ],
    "direction": "vertical"
  },
  "left": {
    "id": "15ae51cef151b6e1",
    "type": "split",
    "children": [
      {
        "id": "4a71139478afcdb2",
        "type": "tabs",
        "children": [
          {
            "id": "a871fdd047fece0e",
            "type": "leaf",
            "state": {
              "type": "file-explorer",
              "state": {
                "sortOrder": "alphabetical"
              }
            }
          },
          {
            "id": "d8a01357311a4b79",
            "type": "leaf",
            "state": {
              "type": "search",
              "state": {
                "query": "簇",
                "matchingCase": false,
                "explainSearch": false,
                "collapseAll": false,
                "extraContext": false,
                "sortOrder": "alphabetical"
              }
            }
          },
          {
            "id": "488bee3550dcad52",
            "type": "leaf",
            "state": {
              "type": "bookmarks",
              "state": {}
            }
          },
          {
            "id": "c91fea3c80cfa66b",
            "type": "leaf",
            "state": {
              "type": "recent-files",
              "state": {}
            }
          }
        ]
      }
    ],
    "direction": "horizontal",
    "width": 300.5
  },
  "right": {
    "id": "31ef4c90174660b7",
    "type": "split",
    "children": [
      {
        "id": "d3db33ff7d0562d4",
        "type": "tabs",
        "children": [
          {
            "id": "5b42c910bf6c3a0d",
            "type": "leaf",
            "state": {
              "type": "backlink",
              "state": {
                "file": "_posts/2023-10-23-传输层3.4.md",
                "collapseAll": false,
                "extraContext": false,
                "sortOrder": "alphabetical",
                "showSearch": false,
                "searchQuery": "",
                "backlinkCollapsed": false,
                "unlinkedCollapsed": true
              }
            }
          },
          {
            "id": "49b79cef2a0b22bc",
            "type": "leaf",
            "state": {
              "type": "outgoing-link",
              "state": {
                "file": "_posts/2023-10-23-传输层3.4.md",
                "linksCollapsed": false,
                "unlinkedCollapsed": true
              }
            }
          },
          {
            "id": "c737b26439bb38b6",
            "type": "leaf",
            "state": {
              "type": "tag",
              "state": {
                "sortOrder": "frequency",
                "useHierarchy": true
              }
            }
          },
          {
            "id": "d5234f8f162d92ed",
            "type": "leaf",
            "state": {
              "type": "outline",
              "state": {
                "file": "_posts/2023-10-23-传输层3.4.md"
              }
            }
          },
          {
            "id": "2ce1c2475db0c5bc",
            "type": "leaf",
            "state": {
              "type": "all-properties",
              "state": {
                "sortOrder": "frequency"
              }
            }
          },
          {
            "id": "81bd272d48c0950e",
            "type": "leaf",
            "state": {
              "type": "file-properties",
              "state": {
                "file": "_posts/2023-10-23-传输层3.4.md"
              }
            }
          }
        ],
        "currentTab": 5
      }
    ],
    "direction": "horizontal",
    "width": 279.5,
    "collapsed": true
  },
  "left-ribbon": {
    "hiddenItems": {
      "switcher:打开快速切换": false,
      "graph:查看关系图谱": false,
      "canvas:新建白板": false,
      "daily-notes:打开/创建今天的日记": false,
      "templates:插入模板": false,
      "command-palette:打开命令面板": false
    }
  },
  "active": "4f8f443e8b801402",
  "lastOpenFiles": [
    "assets/images/Snipaste_2023-10-23_16-46-23.png",
    "_posts/2023-10-23-传输层3.3.md",
    "_posts/2023-10-23-传输层3.4.md",
    "assets/images/Snipaste_2023-10-23_16-43-24.png",
    "assets/images/Snipaste_2023-10-23_16-39-39.png",
    "_posts/2023-10-11-传输层3.2.md",
    "assets/images/Snipaste_2023-10-23_16-27-41.png",
    "assets/images/Snipaste_2023-10-23_16-17-09.png",
    "Pasted image 20230904201810.png",
    "Pasted image 20230904202104.png",
    "Pasted image 20230904202107.png",
    "assets/Pasted image 20231023162627.png",
    "_posts/2023-09-25-应用层2.8.md",
    "_posts/2023-10-09-传输层3.1.md",
    "assets/images/Snipaste_2023-09-25_23-04-06.png",
    "_posts/2023-09-22-并查集.md",
    "_posts/2023-09-20-应用层2.7.md",
    "assets/images/Snipaste_2023-09-25_22-23-11.png",
    "_posts/2023-07-30-markdown语法.md",
    "_posts/2023-09-01-python命名规范.md",
    "_posts/2023-09-18-应用层2.6.md",
    "_posts/2023-09-15-应用层2.3.md",
    "_posts/2023-09-14-应用层2.2.md",
    "_site/计网笔记/2023/09/18/应用层2.6.html",
    "_site/计网笔记/2023/09/18",
    "_site/计网笔记/2023/09/16/应用层2.5.html",
    "_site/计网笔记/2023/09/16",
    "_posts/2023-09-16-应用层2.5.md",
    "_posts/2023-09-15-应用层2.4.md",
    "assets/images/Snipaste_2023-09-16_20-45-43.png.~tmp",
    "_site/计网笔记/2023/09/14/应用层2.2.html",
    "_site/计网笔记/2023/09/14",
    "_site/计网笔记/2023/09/12/应用层2.1.html",
    "_site/计网笔记/2023/09/12",
    "_site/计网笔记/2023/09/09/计算机网络和因特网1.8.html",
    "_posts/2023-09-12-应用层2.1.md",
    "_posts/2023-09-04-计算机网络和因特网1.4.md",
    "_posts/2023-09-08-计算机网络和因特网1.5.md",
    "_posts/2023-09-08-计算机网络和因特网1.6.md",
    "_posts/2023-09-09-计算机网络和因特网1.7.md",
    "_posts/2023-09-09-计算机网络和因特网1.8.md",
    "_posts/2023-09-03-计算机网络和因特网1.3.md",
    "_posts/2023-09-02-计算机网络和因特网1.1.md",
    "_posts/2023-09-02-计算机网络和因特网1.2.md",
    "(/assets/images/home.jpg.md",
    "assets/images.md"
  ]
}